uart_rx_FSM.v
module uart_rx_FSM(
	input clk,
	input rst_n,
	input rx_stable,
	input sample_now,
	input glitch_detected,
	output reg[7:0] rx_data,
	output reg rx_data_valid
);
	parameter idle = 0, start = 1, data = 2, stop = 3;
	reg[2:0] state, next_state;
	reg[2:0] cnt;
	reg[7:0] shift_reg;

	always @(*)begin
		next_state = state;
		case(state)
			idle: next_state = (rx_stable == 1'b0) ? start : idle;
			start:begin
					if(glitch_detected)begin
						next_state = idle;
					end else if(sample_now)begin
						next_state = data;
					end
				end
			data:begin
					if(sample_now && (cnt == 3'd7))begin
						next_state = stop;
					end
				end
			stop:begin
			     		if(sample_now)begin
						next_state = idle;
					end	
			end
				default: next_state = idle;
		endcase
	end



	always @(posedge clk or negedge rst_n)begin
		if(!rst_n)begin
			state <= idle;
		end else begin
			state <= next_state;
		end
	end

	always @(posedge clk or negedge rst_n)begin
		if(!rst_n)begin
			shift_reg	<= 8'd0;
			rx_data		<= 8'd0;
			rx_data_valid	<= 1'd0;
		end  else begin
			rx_data_valid	<= 1'd0;
			case(state)
			idle: shift_reg <= 8'd0;

			data:begin
				if(sample_now)begin
					shift_reg	<={rx_stable, shift_reg[7:1]};
				end
			end
			stop:begin
				if(sample_now)begin
					rx_data		<= shift_reg;
					rx_data_valid	<= 1'b1;
				end		
			end
			endcase
		end
	end

	always @(posedge clk or negedge rst_n)begin
		if(!rst_n)begin
			cnt <= 3'd0;
		end else begin
			if(state==data)begin
				if(sample_now)begin
					if(cnt==3'd7)begin
						cnt <= 3'd0;
					end else begin
						cnt <= cnt + 1'b1;
					end
				end
			end else begin
				cnt <= 3'd0;
			end
		end
	end

endmodule

uart_rx_FSM_tb.v
`timescale 1ns / 1ps

module tb_uart_rx_FSM();

    // 1. 宣告連接到被測 FSM 的訊號
    reg        clk;
    reg        rst_n;
    reg        rx_stable;
    reg        sample_now;
    reg        glitch_detected;
    
    wire [7:0] rx_data;
    wire       rx_data_valid;

    // 2. 實例化你的 FSM 模組
    uart_rx_FSM u_fsm (
        .clk             (clk),
        .rst_n           (rst_n),
        .rx_stable       (rx_stable),
        .sample_now      (sample_now),
        .glitch_detected (glitch_detected),
        .rx_data         (rx_data),
        .rx_data_valid   (rx_data_valid)
    );

    // 3. 產生 50MHz 系統時脈 (週期 20ns)
    always #10 clk = ~clk;

    // 4. 主要測試流程
    integer i;
    reg [7:0] test_pattern;

    initial begin
        // 設定波形輸出
        $dumpfile("fsm_wave.vcd");
        $dumpvars(0, tb_uart_rx_FSM);

        // 初始狀態：UART 閒置時為高電位，控制脈衝皆為 0
        clk             = 0;
        rst_n           = 0;
        rx_stable       = 1'b1;
        sample_now      = 1'b0;
        glitch_detected = 1'b0;

        // 執行系統重置
        #100;
        rst_n = 1;
        #40;

        // ========================================================
        // 實驗一：傳送真貨字元 8'h5A (二進制: 8'b0101_1010)
        // LSB 先傳順序: 0 -> 1 -> 0 -> 1 -> 0 -> 1 -> 0 -> 1
        // ========================================================
        $display("[%0t ns] ======= 實驗一：開始測試真貨接收 =======", $time);
        test_pattern = 8'h5A;

        // 【步驟 A】 降臨 Start Bit (rx_stable 變 0)
        // 這一拍大腦應該要從 idle 變 start
        rx_stable = 1'b0; 
        #20; 

        // 【步驟 B】 模擬計時器在第 8 格抽查通過，噴出 sample_now 脈衝
        // 這一拍大腦應該要從 start 變 data
        sample_now = 1'b1;
        #20;
        sample_now = 1'b0;
        #100; // 模擬格子中間的空白時間

        // 【步驟 C】 依序傳送 8 個 Data bits
        // 每隔一段時間，我們就換下一個 bit，並讓 sample_now 彈起來一拍
        for (i = 0; i < 8; i = i + 1) begin
            rx_stable = test_pattern[i]; // 把 bit 放到線路上
            #100;                         // 讓線路穩定一下
            
            sample_now = 1'b1;            // 模擬計時器在 bit 正中間高喊 sample_now!
            #20;
            sample_now = 1'b0;            // 脈衝放完
            #100;                         // 走完這個 bit 的剩餘時間
        end

        // 【步驟 D】 進到 Stop Bit 狀態 (rx_stable 彈回 1)
        rx_stable = 1'b1;
        #100;
        
        // 模擬計時器在 Stop bit 正中間發出最後一發 sample_now
        // 這一拍 rx_data 應該定稿，且 rx_data_valid 應該拉高一拍，大腦隨後回 idle
        sample_now = 1'b1;
        #20;
        sample_now = 1'b0;

        #200; // 讓大腦在 idle 休息一下下

        // ========================================================
        // 實驗二：測試「雜訊防禦」
        // ========================================================
        $display("[%0t ns] ======= 實驗二：開始測試雜訊防禦 =======", $time);
        
        // 模擬線路短暫掉到 0 (誤以為是 Start Bit)
        // 大腦從 idle 跳進 start
        rx_stable = 1'b0;
        #20;

        // 模擬計時器走到第 8 格發現是假貨，大喊 glitch_detected!
        // 這一拍大腦應該要乖乖跳回 idle，不能進 data
        glitch_detected = 1'b1;
        #20;
        glitch_detected = 1'b0;
        rx_stable = 1'b1; // 線路彈回高電位

        #200;
        $display("[%0t ns] FSM 專屬測試全部結束！", $time);
        $finish;
    end

    // 5. 監聽螢幕輸出
    always @(posedge clk) begin
        if (rx_data_valid) begin
            $display("--------------------------------------------------");
            $display("[%0t ns] 🎉 FSM 大腦成功解鎖並定稿輸出！", $time);
            $display("         解出數值 rx_data = 8'h%h", rx_data);
            $display("--------------------------------------------------");
        end
    end

endmodule

fsm_wave.vcd
$date
	Tue May 26 17:35:14 2026
$end
$version
	Icarus Verilog
$end
$timescale
	1ps
$end
$scope module tb_uart_rx_FSM $end
$var wire 1 ! rx_data_valid $end
$var wire 8 " rx_data [7:0] $end
$var reg 1 # clk $end
$var reg 1 $ glitch_detected $end
$var reg 1 % rst_n $end
$var reg 1 & rx_stable $end
$var reg 1 ' sample_now $end
$var reg 8 ( test_pattern [7:0] $end
$var integer 32 ) i [31:0] $end
$scope module u_fsm $end
$var wire 1 # clk $end
$var wire 1 $ glitch_detected $end
$var wire 1 % rst_n $end
$var wire 1 & rx_stable $end
$var wire 1 ' sample_now $end
$var reg 3 * cnt [2:0] $end
$var reg 3 + next_state [2:0] $end
$var reg 8 , rx_data [7:0] $end
$var reg 1 ! rx_data_valid $end
$var reg 8 - shift_reg [7:0] $end
$var reg 3 . state [2:0] $end
$upscope $end
$upscope $end
$enddefinitions $end
#0
$dumpvars
b0 .
b0 -
b0 ,
b0 +
b0 *
bx )
bx (
0'
1&
0%
0$
0#
b0 "
0!
$end
#10000
1#
#20000
0#
#30000
1#
#40000
0#
#50000
1#
#60000
0#
#70000
1#
#80000
0#
#90000
1#
#100000
0#
1%
#110000
1#
#120000
0#
#130000
1#
#140000
b1 +
0#
0&
b1011010 (
#150000
b1 .
1#
#160000
b10 +
0#
1'
#170000
b10 .
1#
#180000
0#
0'
#190000
1#
#200000
0#
#210000
1#
#220000
0#
#230000
1#
#240000
0#
#250000
1#
#260000
0#
#270000
1#
#280000
0#
b0 )
#290000
1#
#300000
0#
#310000
1#
#320000
0#
#330000
1#
#340000
0#
#350000
1#
#360000
0#
#370000
1#
#380000
0#
1'
#390000
b1 *
1#
#400000
0#
0'
#410000
1#
#420000
0#
#430000
1#
#440000
0#
#450000
1#
#460000
0#
#470000
1#
#480000
0#
#490000
1#
#500000
0#
1&
b1 )
#510000
1#
#520000
0#
#530000
1#
#540000
0#
#550000
1#
#560000
0#
#570000
1#
#580000
0#
#590000
1#
#600000
0#
1'
#610000
b10 *
b10000000 -
1#
#620000
0#
0'
#630000
1#
#640000
0#
#650000
1#
#660000
0#
#670000
1#
#680000
0#
#690000
1#
#700000
0#
#710000
1#
#720000
0#
0&
b10 )
#730000
1#
#740000
0#
#750000
1#
#760000
0#
#770000
1#
#780000
0#
#790000
1#
#800000
0#
#810000
1#
#820000
0#
1'
#830000
b1000000 -
b11 *
1#
#840000
0#
0'
#850000
1#
#860000
0#
#870000
1#
#880000
0#
#890000
1#
#900000
0#
#910000
1#
#920000
0#
#930000
1#
#940000
0#
1&
b11 )
#950000
1#
#960000
0#
#970000
1#
#980000
0#
#990000
1#
#1000000
0#
#1010000
1#
#1020000
0#
#1030000
1#
#1040000
0#
1'
#1050000
b100 *
b10100000 -
1#
#1060000
0#
0'
#1070000
1#
#1080000
0#
#1090000
1#
#1100000
0#
#1110000
1#
#1120000
0#
#1130000
1#
#1140000
0#
#1150000
1#
#1160000
0#
b100 )
#1170000
1#
#1180000
0#
#1190000
1#
#1200000
0#
#1210000
1#
#1220000
0#
#1230000
1#
#1240000
0#
#1250000
1#
#1260000
0#
1'
#1270000
b11010000 -
b101 *
1#
#1280000
0#
0'
#1290000
1#
#1300000
0#
#1310000
1#
#1320000
0#
#1330000
1#
#1340000
0#
#1350000
1#
#1360000
0#
#1370000
1#
#1380000
0#
0&
b101 )
#1390000
1#
#1400000
0#
#1410000
1#
#1420000
0#
#1430000
1#
#1440000
0#
#1450000
1#
#1460000
0#
#1470000
1#
#1480000
0#
1'
#1490000
b110 *
b1101000 -
1#
#1500000
0#
0'
#1510000
1#
#1520000
0#
#1530000
1#
#1540000
0#
#1550000
1#
#1560000
0#
#1570000
1#
#1580000
0#
#1590000
1#
#1600000
0#
1&
b110 )
#1610000
1#
#1620000
0#
#1630000
1#
#1640000
0#
#1650000
1#
#1660000
0#
#1670000
1#
#1680000
0#
#1690000
1#
#1700000
0#
1'
#1710000
b11 +
b10110100 -
b111 *
1#
#1720000
b10 +
0#
0'
#1730000
1#
#1740000
0#
#1750000
1#
#1760000
0#
#1770000
1#
#1780000
0#
#1790000
1#
#1800000
0#
#1810000
1#
#1820000
0#
0&
b111 )
#1830000
1#
#1840000
0#
#1850000
1#
#1860000
0#
#1870000
1#
#1880000
0#
#1890000
1#
#1900000
0#
#1910000
1#
#1920000
b11 +
0#
1'
#1930000
b0 +
b0 *
b1011010 -
b11 .
1#
#1940000
b11 +
0#
0'
#1950000
1#
#1960000
0#
#1970000
1#
#1980000
0#
#1990000
1#
#2000000
0#
#2010000
1#
#2020000
0#
#2030000
1#
#2040000
0#
1&
b1000 )
#2050000
1#
#2060000
0#
#2070000
1#
#2080000
0#
#2090000
1#
#2100000
0#
#2110000
1#
#2120000
0#
#2130000
1#
#2140000
b0 +
0#
1'
#2150000
b0 .
1!
b1011010 "
b1011010 ,
1#
#2160000
0#
0'
#2170000
b0 -
0!
1#
#2180000
0#
#2190000
1#
#2200000
0#
#2210000
1#
#2220000
0#
#2230000
1#
#2240000
0#
#2250000
1#
#2260000
0#
#2270000
1#
#2280000
0#
#2290000
1#
#2300000
0#
#2310000
1#
#2320000
0#
#2330000
1#
#2340000
0#
#2350000
1#
#2360000
b1 +
0#
0&
#2370000
b1 .
1#
#2380000
b0 +
0#
1$
#2390000
b1 +
b0 .
1#
#2400000
b0 +
0#
1&
0$
